pydesync/__init__.py
pydesync/all.py
pydesync-0.1.3.dist-info/LICENSE
pydesync-0.1.3.dist-info/METADATA
pydesync-0.1.3.dist-info/WHEEL
pydesync-0.1.3.dist-info/top_level.txt
pydesync-0.1.3.dist-info/RECORD
