Metadata-Version: 2.1
Name: pydesync
Version: 0.1.3
Summary: Convert async functions to sync and vice versa.
Author-email: Piotr Mardziel <piotrm@gmail.com>
Project-URL: Homepage, https://github.com/piotrm0/pydesync
Project-URL: Bug Tracker, https://github.com/piotrm0/pydesync/issues
Classifier: Programming Language :: Python :: 3
Classifier: License :: OSI Approved :: Artistic License
Classifier: Operating System :: OS Independent
Requires-Python: >=3.8
License-File: LICENSE
